word_search_generator/__init__.py
word_search_generator/__main__.py
word_search_generator/cli.py
word_search_generator/console.py
word_search_generator/core/__init__.py
word_search_generator/core/directions.py
word_search_generator/core/formatter.py
word_search_generator/core/game.py
word_search_generator/core/generator.py
word_search_generator/core/validator.py
word_search_generator/core/word.py
word_search_generator/data/.DS_Store
word_search_generator/data/amphibians.txt
word_search_generator/data/animals.txt
word_search_generator/data/art.txt
word_search_generator/data/automotive.txt
word_search_generator/data/birds.txt
word_search_generator/data/chess.txt
word_search_generator/data/christmas.txt
word_search_generator/data/coastal.txt
word_search_generator/data/countries.txt
word_search_generator/data/desserts.txt
word_search_generator/data/dictionary.txt
word_search_generator/data/dogs.txt
word_search_generator/data/elementary.txt
word_search_generator/data/elements.txt
word_search_generator/data/fish.txt
word_search_generator/data/fruits.txt
word_search_generator/data/geography.txt
word_search_generator/data/greek_alphabet.txt
word_search_generator/data/greek_gods.txt
word_search_generator/data/halloween.txt
word_search_generator/data/history.txt
word_search_generator/data/insects.txt
word_search_generator/data/kitchen.txt
word_search_generator/data/literature.txt
word_search_generator/data/math.txt
word_search_generator/data/meats.txt
word_search_generator/data/medicine.txt
word_search_generator/data/mlb.txt
word_search_generator/data/mls.txt
word_search_generator/data/months.txt
word_search_generator/data/music.txt
word_search_generator/data/nba.txt
word_search_generator/data/nfl.txt
word_search_generator/data/nhl.txt
word_search_generator/data/pirates.txt
word_search_generator/data/science.txt
word_search_generator/data/soccer_clubs.txt
word_search_generator/data/space.txt
word_search_generator/data/sports.txt
word_search_generator/data/technology.txt
word_search_generator-5.0.0.dist-info/WHEEL
word_search_generator-5.0.0.dist-info/entry_points.txt
word_search_generator-5.0.0.dist-info/METADATA
word_search_generator-5.0.0.dist-info/RECORD
