Metadata-Version: 2.4
Name: word-search-generator
Version: 5.0.0
Summary: Make awesome Word Search puzzles
Keywords: puzzles,games,word-search
Author: Josh Duncan
Author-email: Josh Duncan <joshbduncan@gmail.com>
License-Expression: MIT
Classifier: Intended Audience :: End Users/Desktop
Classifier: Natural Language :: English
Classifier: Operating System :: OS Independent
Classifier: Programming Language :: Python
Classifier: Programming Language :: Python :: 3.11
Classifier: Programming Language :: Python :: 3.12
Classifier: Programming Language :: Python :: 3.13
Classifier: Programming Language :: Python :: 3.14
Classifier: Topic :: Games/Entertainment :: Puzzle Games
Classifier: Typing :: Typed
Requires-Dist: fpdf2==2.8.4
Requires-Dist: pillow==12.0.0
Requires-Dist: rich==14.2.0
Requires-Dist: ordered-set>=4.0.0
Requires-Python: >=3.11
Project-URL: bug-tracker, https://github.com/joshbduncan/word-search-generator/issues
Project-URL: changelog, https://github.com/joshbduncan/word-search-generator/blob/main/CHANGLOG.md
Project-URL: documentation, https://github.com/joshbduncan/word-search-generator/wiki
Project-URL: homepage, https://github.com/joshbduncan/word-search-generator
Project-URL: repository, https://github.com/joshbduncan/word-search-generator.git
